basic_panic/__init__.py
basic_panic/panic.py
basic_panic-0.1.1.dist-info/LICENSE
basic_panic-0.1.1.dist-info/METADATA
basic_panic-0.1.1.dist-info/WHEEL
basic_panic-0.1.1.dist-info/RECORD
