Metadata-Version: 2.1
Name: basic-panic
Version: 0.1.1
Summary: A basic panic model
Author: Hendrik Boeck
Author-email: hendrikboeck.dev@protonmail.com
Requires-Python: >=3.10,<4.0
Classifier: Programming Language :: Python :: 3
Classifier: Programming Language :: Python :: 3.10
Classifier: Programming Language :: Python :: 3.11
Classifier: Programming Language :: Python :: 3.12
